acfunsdk/__init__.py
acfunsdk/base.py
acfunsdk/exceptions.py
acfunsdk/page/__init__.py
acfunsdk/page/acer.py
acfunsdk/page/album.py
acfunsdk/page/article.py
acfunsdk/page/bangumi.py
acfunsdk/page/channel.py
acfunsdk/page/comment.py
acfunsdk/page/danmaku.py
acfunsdk/page/doodle.py
acfunsdk/page/extra.py
acfunsdk/page/index.py
acfunsdk/page/live.py
acfunsdk/page/member.py
acfunsdk/page/message.py
acfunsdk/page/moment.py
acfunsdk/page/rank.py
acfunsdk/page/search.py
acfunsdk/page/utils.py
acfunsdk/page/video.py
acfunsdk/source.py
acfunsdk-0.9.7.dist-info/LICENSE
acfunsdk-0.9.7.dist-info/WHEEL
acfunsdk-0.9.7.dist-info/METADATA
acfunsdk-0.9.7.dist-info/RECORD
