Metadata-Version: 2.1
Name: acfunsdk
Version: 0.9.7
Summary: acfunsdk - UNOFFICEICAL
Home-page: https://pypi.org/project/acfunsdk/
License: MIT
Keywords: acfun,sdk,acfunsdk,unofficeical
Author: dolacmeo
Author-email: dolacmeo@gmail.com
Requires-Python: >=3.8,<4.0
Classifier: Development Status :: 4 - Beta
Classifier: Environment :: Console
Classifier: Intended Audience :: Developers
Classifier: License :: OSI Approved :: MIT License
Classifier: Natural Language :: Chinese (Simplified)
Classifier: Natural Language :: English
Classifier: Operating System :: Microsoft :: Windows
Classifier: Operating System :: Microsoft :: Windows :: Windows 10
Classifier: Programming Language :: Python :: 3
Classifier: Programming Language :: Python :: 3.8
Classifier: Programming Language :: Python :: 3.9
Classifier: Programming Language :: Python :: 3.10
Classifier: Programming Language :: Python :: 3
Classifier: Programming Language :: Python :: 3.10
Classifier: Programming Language :: Python :: 3.7
Classifier: Programming Language :: Python :: 3.8
Classifier: Programming Language :: Python :: 3.9
Classifier: Topic :: Education
Classifier: Topic :: Internet :: WWW/HTTP :: Browsers
Classifier: Topic :: Software Development :: Libraries
Requires-Dist: beautifulsoup4 (>=4,<5)
Requires-Dist: httpx (>=0.23,<0.24)
Requires-Dist: lxml (>=4,<5)
Project-URL: Bug Tracker, https://github.com/dolaCmeo/acfunsdk/issues
Project-URL: Documentation, https://github.com/dolaCmeo/acfunsdk
Project-URL: Repository, https://github.com/dolaCmeo/acfunsdk
